[
  {
    "name": "你的可爱老婆",
    "baidu": "https://pan.baidu.com/s/1wTT19oaFGS-M-QUO5whWLw?pwd=xcyx",
    "quark": "https://pan.quark.cn/s/949433e55e9a",
    "isNew": true
  },
  {
    "name": "书中自有颜如玉",
    "baidu": "https://pan.baidu.com/s/1uz7bCiXVz5C0sIMe-k-49Q?pwd=xcyx",
    "quark": "https://pan.quark.cn/s/3a690cadd064",
    "isNew": true
  },
  {
    "name": "东北往事",
    "baidu": "https://pan.baidu.com/s/1QQJAUB6QfJk5qHkLyBx4ig?pwd=xcyx",
    "quark": "https://pan.quark.cn/s/d3afdaa9c2e2",
    "isNew": true
  },
  {
    "name": "Miss World世界小姐养成日记",
    "baidu": "https://pan.baidu.com/s/1wM-k6eTljar6sIV_xcrwaQ?pwd=xcyx",
    "quark": "https://pan.quark.cn/s/a217e55f4556",
    "isNew": true
  },
  {
    "name": "转生为仓鼠的我与三姐妹的甜蜜生活 demo",
    "baidu": "https://pan.baidu.com/s/1MguMjfyj3JAA6uMqJp14fA?pwd=xcyx",
    "quark": "https://pan.quark.cn/s/6fffee645b06",
    "isNew": true
  },
  {
    "name": "SB帝国 v20250221",
    "baidu": "https://pan.baidu.com/s/1DltDXjAlQHxnBovuLtGdEw?pwd=xcyx",
    "quark": "https://pan.quark.cn/s/a4e665f02459",
    "isNew": false
  },
  {
    "name": "【已修复】女王的游戏：盛世天下 媚娘篇 Build.22921822",
    "baidu": "https://pan.baidu.com/s/1Fc7_VLr03bvedUTDXNDWRQ?pwd=xcyx",
    "quark": "https://pan.quark.cn/s/09b4c83abceb",
    "isNew": false
  },
  {
    "name": "三日危情，独家的记忆 v20240930",
    "baidu": "https://pan.baidu.com/s/1XZp6MIyjlKvWXq_6JhqJWQ?pwd=xcyx",
    "quark": "https://pan.quark.cn/s/f95b5f5187fa",
    "isNew": false
  },
  {
    "name": "不好啦！师父被女妖精抓走了！ Build.22258419",
    "baidu": "https://pan.baidu.com/s/1d18eY47TrPVbEh0ARdfgNg?pwd=xcyx",
    "quark": "https://pan.quark.cn/s/c506c4329d49",
    "isNew": false
  },
  {
    "name": "主播之心 v20250430",
    "baidu": "https://pan.baidu.com/s/1Qeo59HVLBjwuLrLfx9KlWQ?pwd=xcyx",
    "quark": "https://pan.quark.cn/s/dfe6e1834f14",
    "isNew": false
  },
  {
    "name": "代号三国：龙起 Build.23143939",
    "baidu": "https://pan.baidu.com/s/1oJHlH0kOuvFMoF8VKx6T3Q?pwd=xcyx",
    "quark": "https://pan.quark.cn/s/66f2f30f4e92",
    "isNew": false
  },
  {
    "name": "你好！我们还有场恋爱没谈 v20250604",
    "baidu": "https://pan.baidu.com/s/1Acl5CXHierSkEcA_p66Wkg?pwd=xcyx",
    "quark": "https://pan.quark.cn/s/18fb4424bcb0",
    "isNew": false
  },
  {
    "name": "你好，你配吗？ Build.22863638",
    "baidu": "https://pan.baidu.com/s/1fvHNaho82gEO3mIJQe3wGA?pwd=xcyx",
    "quark": "https://pan.quark.cn/s/371f1234eca5",
    "isNew": false
  },
  {
    "name": "侦探，请守护我的秘密吧 v20250516",
    "baidu": "https://pan.baidu.com/s/18rPGXfbdqovurRoJ_Y3qFQ?pwd=xcyx",
    "quark": "https://pan.quark.cn/s/95d15ec2e148",
    "isNew": false
  },
  {
    "name": "做你的猫 v202409016",
    "baidu": "https://pan.baidu.com/s/1xo_dp9Pd5qfiv3uqlaQGMQ?pwd=xcyx",
    "quark": "https://pan.quark.cn/s/a17b2297ea20",
    "isNew": false
  },
  {
    "name": "光影人生 v20250409",
    "baidu": "https://pan.baidu.com/s/1ulHHKVy4aQZG3Gd8FCJsaQ?pwd=xcyx",
    "quark": "https://pan.quark.cn/s/4ffbab8ad3ab",
    "isNew": false
  },
  {
    "name": "冰点之下 Build.23461289",
    "baidu": "https://pan.baidu.com/s/1Gywt5EF8_FF5iHcPsHriAw?pwd=xcyx",
    "quark": "https://pan.quark.cn/s/4d18b59cd273",
    "isNew": false
  },
  {
    "name": "别跑！美女在追你！ Build.13851858",
    "baidu": "https://pan.baidu.com/s/1GhuMI-zcquMVgVizG8Sb5g?pwd=xcyx",
    "quark": "https://pan.quark.cn/s/780403b00819",
    "isNew": false
  },
  {
    "name": "厦日恋旅 Build.22639242",
    "baidu": "https://pan.baidu.com/s/11pz24OhWDHic0AqKlSpoNA?pwd=xcyx",
    "quark": "https://pan.quark.cn/s/bc2d1f673597",
    "isNew": false
  },
  {
    "name": "合租恋人：恋爱进行时 Build.23249832",
    "baidu": "https://pan.baidu.com/s/1oHAbCMYzbuZio1JucJGiwA?pwd=xcyx",
    "quark": "https://pan.quark.cn/s/6111d1ba17a1",
    "isNew": false
  },
  {
    "name": "名利游戏 Build.18111147",
    "baidu": "https://pan.baidu.com/s/1Ssx6vpXjI-TTxIFmblliMg?pwd=xcyx",
    "quark": "https://pan.quark.cn/s/4a833b81653f",
    "isNew": false
  },
  {
    "name": "后宫佳丽999 v1.0.2.2",
    "baidu": "https://pan.baidu.com/s/1fv0JJPr4WC05ZCXhbIIXQQ?pwd=xcyx",
    "quark": "https://pan.quark.cn/s/24bde95254b7",
    "isNew": false
  },
  {
    "name": "命运游戏2：百年之约 v0.1.0",
    "baidu": "https://pan.baidu.com/s/1O9ph8d813G7g5p5VsmrF0w?pwd=xcyx",
    "quark": "https://pan.quark.cn/s/cc506ca90307",
    "isNew": false
  },
  {
    "name": "命运游戏：逆时寻凶 v0.1.2",
    "baidu": "https://pan.baidu.com/s/1TvCyHW2ZjnEjKUaaU8qBxA?pwd=xcyx",
    "quark": "https://pan.quark.cn/s/5faf60d4d53f",
    "isNew": false
  },
  {
    "name": "咸鱼殿下 v20250716",
    "baidu": "https://pan.baidu.com/s/1Wfcb0K0s-jpq7jTR55EVOw?pwd=xcyx",
    "quark": "https://pan.quark.cn/s/187dc54ac2c1",
    "isNew": false
  },
  {
    "name": "嘘，美女拍摄中 v20251222",
    "baidu": "https://pan.baidu.com/s/1OZYpnOvYnvO4DqS2hwHUvA?pwd=xcyx",
    "quark": "https://pan.quark.cn/s/7d762d84e627",
    "isNew": false
  },
  {
    "name": "嘟嘟嘟~恋爱信号响不停，美女室友们教我如何淡定？ Build.22173934",
    "baidu": "https://pan.baidu.com/s/1avRqMbMC7F6IXifMswwMmA?pwd=xcyx",
    "quark": "https://pan.quark.cn/s/646e892a96f3",
    "isNew": false
  },
  {
    "name": "夏日美女：欧巴请和我恋爱吧！v20260408",
    "baidu": "https://pan.baidu.com/s/1cuzHHx9TP_5-WDxQ65iCig?pwd=xcyx",
    "quark": "https://pan.quark.cn/s/23f781f39051",
    "isNew": false
  },
  {
    "name": "夜店高手之御女心经 v20250405",
    "baidu": "https://pan.baidu.com/s/1moaEA7TgYSQuRH3B-jXlRQ?pwd=xcyx",
    "quark": "https://pan.quark.cn/s/6db618234ab2",
    "isNew": false
  },
  {
    "name": "夜蒲觅爱 v20240904",
    "baidu": "https://pan.baidu.com/s/1S_z2dpRllbcTWs6m-zRwCg?pwd=xcyx",
    "quark": "https://pan.quark.cn/s/5bae09c07663",
    "isNew": false
  },
  {
    "name": "天命重启：心跳的抉择 v20251022",
    "baidu": "https://pan.baidu.com/s/1kznaeXxlyAJOFkQmstgBxw?pwd=xcyx",
    "quark": "https://pan.quark.cn/s/75b2791d20ab",
    "isNew": false
  },
  {
    "name": "天地有私，宿命之主 v20250714",
    "baidu": "https://pan.baidu.com/s/1Kt453O20qIeNRl5wqLZsuQ?pwd=xcyx",
    "quark": "https://pan.quark.cn/s/c0ce75a314a2",
    "isNew": false
  },
  {
    "name": "失业了，我获得了亿万游戏财产 v1.0.0",
    "baidu": "https://pan.baidu.com/s/1AKCRYqiLd6LnG1H7I8v8wQ?pwd=xcyx",
    "quark": "https://pan.quark.cn/s/db96cd9a7d6d",
    "isNew": false
  },
  {
    "name": "失恋玩家 Build.23077418",
    "baidu": "https://pan.baidu.com/s/1dMniRRyjjp1Ou49mN8mquA?pwd=xcyx",
    "quark": "https://pan.quark.cn/s/b14f7b3a232d",
    "isNew": false
  },
  {
    "name": "奔跑 Build.21738439",
    "baidu": "https://pan.baidu.com/s/1wDu05Wa6QF_lemZ9S5fXGA?pwd=xcyx",
    "quark": "https://pan.quark.cn/s/91451cc5bb15",
    "isNew": false
  },
  {
    "name": "女神保卫战：我的同居女神竟是小姨子 Build.14702856",
    "baidu": "https://pan.baidu.com/s/1u2HgqNBviMKu64AAm4q9QA?pwd=xcyx",
    "quark": "https://pan.quark.cn/s/ddf663de5471",
    "isNew": false
  },
  {
    "name": "女神氪金系统 v20250427",
    "baidu": "https://pan.baidu.com/s/1F_yeVpAS_yN3JiJC7IsDnw?pwd=xcyx",
    "quark": "https://pan.quark.cn/s/f2040ca503b3",
    "isNew": false
  },
  {
    "name": "女神的贴身男仆 Build.21828100",
    "baidu": "https://pan.baidu.com/s/1wDbgapocFsPWszJkWRQ4BA?pwd=xcyx",
    "quark": "https://pan.quark.cn/s/cb7f664bf126",
    "isNew": false
  },
  {
    "name": "女神驾到：夏日甜心",
    "baidu": "https://pan.baidu.com/s/1t1UV5fS74DwqGuzpVpx1kQ?pwd=xcyx",
    "quark": "https://pan.quark.cn/s/f317384e31ff",
    "isNew": false
  },
  {
    "name": "完蛋！我也能追到美女了！ Build.16163347",
    "baidu": "https://pan.baidu.com/s/1lWbgx_Lcio8YauHyLNrQGQ?pwd=xcyx",
    "quark": "https://pan.quark.cn/s/3d1c817cc63c",
    "isNew": false
  },
  {
    "name": "完蛋！我被美女包围了！ v20250701",
    "baidu": "https://pan.baidu.com/s/1PN7F5d9jelR26wEGAiYbmg?pwd=xcyx",
    "quark": "https://pan.quark.cn/s/981a86449a28",
    "isNew": false
  },
  {
    "name": "完蛋！我被美女包围了！2 模拟器版 v1.16.0.233",
    "baidu": "https://pan.baidu.com/s/1Y4QgUvOPtK_Cc_G7QZamDA?pwd=xcyx",
    "quark": "https://pan.quark.cn/s/2bccae6e457a",
    "isNew": false
  },
  {
    "name": "定制女友 v20250709",
    "baidu": "https://pan.baidu.com/s/1Mgf3VBT8Jen23XZfjfX26w?pwd=xcyx",
    "quark": "https://pan.quark.cn/s/6a521a7029a6",
    "isNew": false
  },
  {
    "name": "宝贝别怕，有我在 Build.22436647",
    "baidu": "https://pan.baidu.com/s/1EFVarOCnAIYpHv8fvqm_OQ?pwd=xcyx",
    "quark": "https://pan.quark.cn/s/515170a1fc88",
    "isNew": false
  },
  {
    "name": "对不起！我把美女包围了！ v1.2.0",
    "baidu": "https://pan.baidu.com/s/1LqdIuszxnfXTVKjDQIgNQA?pwd=xcyx",
    "quark": "https://pan.quark.cn/s/9c400675cf04",
    "isNew": false
  },
  {
    "name": "导演模拟器 v2.0.4",
    "baidu": "https://pan.baidu.com/s/1HbDxE_oT0XdiNH6FTZlLUg?pwd=xcyx",
    "quark": "https://pan.quark.cn/s/296e1f51ef19",
    "isNew": false
  },
  {
    "name": "小丑游戏 v20251224",
    "baidu": "https://pan.baidu.com/s/1nd4scxiLa4ifaqWdzFOBDQ?pwd=xcyx",
    "quark": "https://pan.quark.cn/s/a97cbbba55f7",
    "isNew": false
  },
  {
    "name": "开局五个亿 v20241018",
    "baidu": "https://pan.baidu.com/s/11E87CwwExktq5-Z8W6COmg?pwd=xcyx",
    "quark": "https://pan.quark.cn/s/15d714fe0df6",
    "isNew": false
  },
  {
    "name": "异世界归来的我错过了爱情 v20250501",
    "baidu": "https://pan.baidu.com/s/1shW7-750oLUdfgI08KoNaQ?pwd=xcyx",
    "quark": "https://pan.quark.cn/s/f5acce879c86",
    "isNew": false
  },
  {
    "name": "心之岛 Build.22813243",
    "baidu": "https://pan.baidu.com/s/1llPwv1x872a-g-1l7MPzcA?pwd=xcyx",
    "quark": "https://pan.quark.cn/s/47999a68bfa5",
    "isNew": false
  },
  {
    "name": "心动满屋 Build.15088762",
    "baidu": "https://pan.baidu.com/s/1maSUcsi25GdBH54CwG9U4w?pwd=xcyx",
    "quark": "https://pan.quark.cn/s/5d4737c0abd0",
    "isNew": false
  },
  {
    "name": "心跳大冒险：泰遇 Build.20030751",
    "baidu": "https://pan.baidu.com/s/10AArRKGrIJt_HPKRuo9YEw?pwd=xcyx",
    "quark": "https://pan.quark.cn/s/c3f7e31293d5",
    "isNew": false
  },
  {
    "name": "怦然心动的她们 v0.2.0",
    "baidu": "https://pan.baidu.com/s/16wecfc2n8ci7LBQRJpLI1g?pwd=xcyx",
    "quark": "https://pan.quark.cn/s/299732916561",
    "isNew": false
  },
  {
    "name": "恋爱从离别开始 Build.19745890",
    "baidu": "https://pan.baidu.com/s/11rad6024MOtgJyF9dMRy9Q?pwd=xcyx",
    "quark": "https://pan.quark.cn/s/af1189e7ec83",
    "isNew": false
  },
  {
    "name": "恋爱单选题 Build.15147516",
    "baidu": "https://pan.baidu.com/s/1GrrhfHEk4UQ2vEVIjbR7zg?pwd=xcyx",
    "quark": "https://pan.quark.cn/s/0f3bbf7dc83a",
    "isNew": false
  },
  {
    "name": "恋爱秘密侦探社 v0.8.77",
    "baidu": "https://pan.baidu.com/s/14Q8Hq4Fb9M5TcZhcurUpnQ?pwd=xcyx",
    "quark": "https://pan.quark.cn/s/96453b4c2ee3",
    "isNew": false
  },
  {
    "name": "成为皇帝！我的万亿美女星球帝国 Build.22856344",
    "baidu": "https://pan.baidu.com/s/1_GOLruEOatwisWSXLJ4hYA?pwd=xcyx",
    "quark": "https://pan.quark.cn/s/ebf45cb16139",
    "isNew": false
  },
  {
    "name": "我为情狂 v1.1",
    "baidu": "https://pan.baidu.com/s/1ULuwLTpiZI7P8INHy4VeDw?pwd=xcyx",
    "quark": "https://pan.quark.cn/s/7bb4a149bbe6",
    "isNew": false
  },
  {
    "name": "我只是想让她们都幸福 v20251109",
    "baidu": "https://pan.baidu.com/s/1SB1ZnwfsCYN6VHG9oKIOxA?pwd=xcyx",
    "quark": "https://pan.quark.cn/s/c5fa5b3241e9",
    "isNew": false
  },
  {
    "name": "我和七个俏房客 v1.0.5.4491",
    "baidu": "https://pan.baidu.com/s/16q6fbxGfHgrTarf1afLqHQ?pwd=xcyx",
    "quark": "https://pan.quark.cn/s/288b8f48419f",
    "isNew": false
  },
  {
    "name": "我和美女有个约会 v20250822",
    "baidu": "https://pan.baidu.com/s/1fmbl30tgmzuy7xcTnKlDrQ?pwd=xcyx",
    "quark": "https://pan.quark.cn/s/53d713dcf0ea",
    "isNew": false
  },
  {
    "name": "我的同事不对劲 Build.19487778",
    "baidu": "https://pan.baidu.com/s/1DquoN4ED_HoFuQxdNwMPlg?pwd=xcyx",
    "quark": "https://pan.quark.cn/s/de0a59b94518",
    "isNew": false
  },
  {
    "name": "我的机器人女友 Build.22314596",
    "baidu": "https://pan.baidu.com/s/1qwybM_z9ChTiSlB8KiVLIg?pwd=xcyx",
    "quark": "https://pan.quark.cn/s/957c955906c2",
    "isNew": false
  },
  {
    "name": "我被古装美女包围了 Build.13840625",
    "baidu": "https://pan.baidu.com/s/1mSnwT1i5lhSrZkiSCXdQqA?pwd=xcyx",
    "quark": "https://pan.quark.cn/s/f5e0f0036249",
    "isNew": false
  },
  {
    "name": "我靠双修拯救世界 v20241224",
    "baidu": "https://pan.baidu.com/s/1hjDc8saPjW-luxpiC2RtAA?pwd=xcyx",
    "quark": "https://pan.quark.cn/s/86d892de922b",
    "isNew": false
  },
  {
    "name": "捞女游戏 | 情感反诈模拟器 v20250619",
    "baidu": "https://pan.baidu.com/s/1QhKYYDEQ8xIryFNhwd6IpA?pwd=xcyx",
    "quark": "https://pan.quark.cn/s/59beffb9ce66",
    "isNew": false
  },
  {
    "name": "明末：伐定天下 v1.0.63",
    "baidu": "https://pan.baidu.com/s/1PDBYxU_3Lrqg0UUyeAP7uQ?pwd=xcyx",
    "quark": "https://pan.quark.cn/s/b1db1a6ecdbf",
    "isNew": false
  },
  {
    "name": "月亮三部曲 v1.1.4",
    "baidu": "https://pan.baidu.com/s/17A4Ju5uTH1xZuaQ-juK0cQ?pwd=xcyx",
    "quark": "https://pan.quark.cn/s/0a1a1e45c67a",
    "isNew": false
  },
  {
    "name": "有这么一个家伙 Build.20380128",
    "baidu": "https://pan.baidu.com/s/1GV56e5BcmzwFXqshUb_gpg?pwd=xcyx",
    "quark": "https://pan.quark.cn/s/d6faf8b5cc3e",
    "isNew": false
  },
  {
    "name": "梦恋依心 v20250520",
    "baidu": "https://pan.baidu.com/s/1tyRL-Fmrihxx84kMWULYAw?pwd=xcyx",
    "quark": "https://pan.quark.cn/s/a8ec4ed6b1b7",
    "isNew": false
  },
  {
    "name": "欢迎来到林葬屋 v20250912",
    "baidu": "https://pan.baidu.com/s/1Gn_cGfWUWVE65osO0AIinw?pwd=xcyx",
    "quark": "https://pan.quark.cn/s/e506ad5cf23a",
    "isNew": false
  },
  {
    "name": "死亡重启 v1.0.2",
    "baidu": "https://pan.baidu.com/s/1I7mtX2PkSsI4_3YJ3VizFg?pwd=xcyx",
    "quark": "https://pan.quark.cn/s/1372a638d638",
    "isNew": false
  },
  {
    "name": "消失的航班，还有她她她！ v20250521",
    "baidu": "https://pan.baidu.com/s/1rVig8qc-NdG0ahBOieIfpw?pwd=xcyx",
    "quark": "https://pan.quark.cn/s/d11290d69ed2",
    "isNew": false
  },
  {
    "name": "烧尾宴 v20260101",
    "baidu": "https://pan.baidu.com/s/1mMbp9cqP3Hb4dO7ED8wUGg?pwd=xcyx",
    "quark": "https://pan.quark.cn/s/c5388a7edfa4",
    "isNew": false
  },
  {
    "name": "爱情，死亡与比基尼 v20250605",
    "baidu": "https://pan.baidu.com/s/15-NGhoAEifDNmsBjJIYivA?pwd=xcyx",
    "quark": "https://pan.quark.cn/s/acc17e3c28b3",
    "isNew": false
  },
  {
    "name": "男神模拟器 Build.23374790",
    "baidu": "https://pan.baidu.com/s/1lXNyV_QtjSPBao5Ayy8JiQ?pwd=xcyx",
    "quark": "https://pan.quark.cn/s/9457bc039d8d",
    "isNew": false
  },
  {
    "name": "百妖试禅心 v20250721",
    "baidu": "https://pan.baidu.com/s/1IaIB7uKRAgk6Hyc6qH3zQQ?pwd=xcyx",
    "quark": "https://pan.quark.cn/s/536f51255c62",
    "isNew": false
  },
  {
    "name": "相亲攻略之宝贝别再选我了 Build.15292110",
    "baidu": "https://pan.baidu.com/s/1PBNww87A5SWJUNH0QOYV2Q?pwd=xcyx",
    "quark": "https://pan.quark.cn/s/8b6238dc2ec4",
    "isNew": false
  },
  {
    "name": "看不见的我们 v20251122",
    "baidu": "https://pan.baidu.com/s/1wF16VnKuRaC0D3yAfb1gOQ?pwd=xcyx",
    "quark": "https://pan.quark.cn/s/da7ebae78ce6",
    "isNew": false
  },
  {
    "name": "神医西门庆 v20240619",
    "baidu": "https://pan.baidu.com/s/1FiYUj7y0bLk4EFRynKHYTQ?pwd=xcyx",
    "quark": "https://pan.quark.cn/s/bc5651afa40a",
    "isNew": false
  },
  {
    "name": "禁止过分投入 v19",
    "baidu": "https://pan.baidu.com/s/1oQzMFcLCLMWjR2tuskEGwQ?pwd=xcyx",
    "quark": "https://pan.quark.cn/s/76e998d29329",
    "isNew": false
  },
  {
    "name": "禁止过分投入2：夏日大排档 v20251203",
    "baidu": "https://pan.baidu.com/s/1HS4NTdKWSY_D2bYmt68OzA?pwd=xcyx",
    "quark": "https://pan.quark.cn/s/73f688ec5f03",
    "isNew": false
  },
  {
    "name": "离魂界：校怨 v20250110",
    "baidu": "https://pan.baidu.com/s/1gxwl_f9fWdyzWaIftz7lrQ?pwd=xcyx",
    "quark": "https://pan.quark.cn/s/cd47ea3fd9e0",
    "isNew": false
  },
  {
    "name": "糟糕，我要坠入爱河啦 Build.15320283",
    "baidu": "https://pan.baidu.com/s/1Iwevwr7WSl6t89tPz-kQyQ?pwd=xcyx",
    "quark": "https://pan.quark.cn/s/1cca308dc1ef",
    "isNew": false
  },
  {
    "name": "绝世千金重启版 Build.19935615",
    "baidu": "https://pan.baidu.com/s/1A5DCeGubR_OPfGVJ5DrqHg?pwd=xcyx",
    "quark": "https://pan.quark.cn/s/70318b56df4a",
    "isNew": false
  },
  {
    "name": "罪金游戏 Build.22212019",
    "baidu": "https://pan.baidu.com/s/1bFqAJYxORuaezzNZdcJOAg?pwd=xcyx",
    "quark": "https://pan.quark.cn/s/a570ca1b3def",
    "isNew": false
  },
  {
    "name": "美女，请别影响我学习 v20240731",
    "baidu": "https://pan.baidu.com/s/1IK2SLAL6hY-TT4d-1tCX5w?pwd=xcyx",
    "quark": "https://pan.quark.cn/s/166f4270e8a0",
    "isNew": false
  },
  {
    "name": "美女，请别影响我成仙 v20250729",
    "baidu": "https://pan.baidu.com/s/1sX7-ZF99Hlp1-mMR-G9upg?pwd=xcyx",
    "quark": "https://pan.quark.cn/s/4dab152e0163",
    "isNew": false
  },
  {
    "name": "背后 v20241220",
    "baidu": "https://pan.baidu.com/s/1Jmqhdq3Exk1jG2EddCp_ww?pwd=xcyx",
    "quark": "https://pan.quark.cn/s/b0eaa2f18996",
    "isNew": false
  },
  {
    "name": "背后2：异化 v1.0.0",
    "baidu": "https://pan.baidu.com/s/11nuMtWcsSzM7FHg92qNVeg?pwd=xcyx",
    "quark": "https://pan.quark.cn/s/0eb38e850438",
    "isNew": false
  },
  {
    "name": "背后3：阴戏 Build.20153095",
    "baidu": "https://pan.baidu.com/s/1QlTrDWUluWMkgjTFTKJ5Ag?pwd=xcyx",
    "quark": "https://pan.quark.cn/s/9d87fae92c67",
    "isNew": false
  },
  {
    "name": "荒岛恋情 v1.0.28",
    "baidu": "https://pan.baidu.com/s/1GT-h-lJHsHAbCInwM6v-Ig?pwd=xcyx",
    "quark": "https://pan.quark.cn/s/917fd1e30442",
    "isNew": false
  },
  {
    "name": "荒岛求生：逃出美女岛 Build.22298449",
    "baidu": "https://pan.baidu.com/s/1jfhdSLvGtMrRn7jNOv2uZg?pwd=xcyx",
    "quark": "https://pan.quark.cn/s/63a729a1f01c",
    "isNew": false
  },
  {
    "name": "血薪记：罪恶园区 Build.21504525",
    "baidu": "https://pan.baidu.com/s/1BnZB9LI7JbGm6RNaEWv9rA?pwd=xcyx",
    "quark": "https://pan.quark.cn/s/bcc4df82efcf",
    "isNew": false
  },
  {
    "name": "被勒索的主播 Build.22662650",
    "baidu": "https://pan.baidu.com/s/1DVBg1gR1sEEKTeutlp7lDw?pwd=xcyx",
    "quark": "https://pan.quark.cn/s/c9f2e65faddb",
    "isNew": false
  },
  {
    "name": "规则怪谈：盛崖小区 v20241024",
    "baidu": "https://pan.baidu.com/s/1VnA4hPzY3l5G9DEj364ufA?pwd=xcyx",
    "quark": "https://pan.quark.cn/s/743ee664a733",
    "isNew": false
  },
  {
    "name": "许愿，我要带她们回现代 Build.14198409",
    "baidu": "https://pan.baidu.com/s/1w0vNtsvlnQenqqDMcRVjYg?pwd=xcyx",
    "quark": "https://pan.quark.cn/s/4519e67d34d0",
    "isNew": false
  },
  {
    "name": "请不要欺负我，大小姐们！ v20250707",
    "baidu": "https://pan.baidu.com/s/1jRKLlZy1oEgHdY1g5yo9MA?pwd=xcyx",
    "quark": "https://pan.quark.cn/s/5707b6106886",
    "isNew": false
  },
  {
    "name": "请做coser的主人5 v20250516",
    "baidu": "https://pan.baidu.com/s/146Wx3qVPs4M1UNtkh-ZTUA?pwd=xcyx",
    "quark": "https://pan.quark.cn/s/4b368fd880b5",
    "isNew": false
  },
  {
    "name": "贝塔咖啡馆：书写你的爱情故事 Build.22891919",
    "baidu": "https://pan.baidu.com/s/1SDedqsOR9zVxYGLzWJTgRw?pwd=xcyx",
    "quark": "https://pan.quark.cn/s/b2a19c5d3c30",
    "isNew": false
  },
  {
    "name": "超级情圣 v6509984",
    "baidu": "https://pan.baidu.com/s/1xptDyiG3GkD3LFUrvTmU0g?pwd=xcyx",
    "quark": "https://pan.quark.cn/s/9efc09b248ea",
    "isNew": false
  },
  {
    "name": "超级情圣2",
    "baidu": "https://pan.baidu.com/s/1heLqrBSprkkhhUpFFqeEhA?pwd=xcyx",
    "quark": "https://pan.quark.cn/s/507455166f14",
    "isNew": false
  },
  {
    "name": "超级情圣3 v1.0.32",
    "baidu": "https://pan.baidu.com/s/1s_hd1FSEqAn1meHByFYWXw?pwd=xcyx",
    "quark": "https://pan.quark.cn/s/c5711035a54f",
    "isNew": false
  },
  {
    "name": "超级星探 v20240718",
    "baidu": "https://pan.baidu.com/s/1-3zOVwWLEd7DIswwWdNtug?pwd=xcyx",
    "quark": "https://pan.quark.cn/s/0353fc1e1cb7",
    "isNew": false
  },
  {
    "name": "这个CEO我当定了！Build.19773646",
    "baidu": "https://pan.baidu.com/s/16YfI08yL-puG_oFzKKkX9A?pwd=xcyx",
    "quark": "https://pan.quark.cn/s/beb5a3d870a3",
    "isNew": false
  },
  {
    "name": "迷情医院 v20240921",
    "baidu": "https://pan.baidu.com/s/1QBM43oGD1fRl8gygo1g4tQ?pwd=xcyx",
    "quark": "https://pan.quark.cn/s/0b765dd9dd32",
    "isNew": false
  },
  {
    "name": "迷雾审判 v20250714",
    "baidu": "https://pan.baidu.com/s/1dX5w_CqHQxMyUIqjxubOoA?pwd=xcyx",
    "quark": "https://pan.quark.cn/s/6a75128f0650",
    "isNew": false
  },
  {
    "name": "逆光迷途 v3560",
    "baidu": "https://pan.baidu.com/s/1EGn11JuOlDuESqEFm5AJ2w?pwd=xcyx",
    "quark": "https://pan.quark.cn/s/88620368da2a",
    "isNew": false
  },
  {
    "name": "逆袭重启 Build.22128461",
    "baidu": "https://pan.baidu.com/s/1Fy5dZbJN-wGA-uBdoWPZdg?pwd=xcyx",
    "quark": "https://pan.quark.cn/s/1d65ae87a013",
    "isNew": false
  },
  {
    "name": "逆转命运之光 v20250520",
    "baidu": "https://pan.baidu.com/s/1zzNhX9_72v5U2EEQrTCDlQ?pwd=xcyx",
    "quark": "https://pan.quark.cn/s/0bd9b7f235f2",
    "isNew": false
  },
  {
    "name": "都要！小孩子才做选择！ v20240408",
    "baidu": "https://pan.baidu.com/s/1lOna53GfyoX7fmk1_9D8yg?pwd=xcyx",
    "quark": "https://pan.quark.cn/s/adfaeb7f9bd1",
    "isNew": false
  },
  {
    "name": "重生了还要我谈恋爱？Build.15200725",
    "baidu": "https://pan.baidu.com/s/1I_EgJw_U_GY1Ys__73ObYg?pwd=xcyx",
    "quark": "https://pan.quark.cn/s/f685184ea1bc",
    "isNew": false
  },
  {
    "name": "重生！我在古代遇佳人 v1.0.0",
    "baidu": "https://pan.baidu.com/s/1BhA6n8IcismeHZs2xV_ELw?pwd=xcyx",
    "quark": "https://pan.quark.cn/s/ddb8b5d69570",
    "isNew": false
  },
  {
    "name": "阿西, 美女室友竟然...？2 v20251119",
    "baidu": "https://pan.baidu.com/s/17SF0NxC9fSZBMubVph1Bbg?pwd=xcyx",
    "quark": "https://pan.quark.cn/s/e1204c9317a6",
    "isNew": false
  },
  {
    "name": "阿西, 美女室友竟然...？v20241003",
    "baidu": "https://pan.baidu.com/s/1kepMX11x6Y6SHF-F6JGXrw?pwd=xcyx",
    "quark": "https://pan.quark.cn/s/7a4c47578434",
    "isNew": false
  },
  {
    "name": "隐形守护者 v3787400",
    "baidu": "https://pan.baidu.com/s/1cHBFhWBMie-hIDB-3rpFuQ?pwd=xcyx",
    "quark": "https://pan.quark.cn/s/f4b2af198178",
    "isNew": false
  },
  {
    "name": "难忘的爱 Build.23558171",
    "baidu": "https://pan.baidu.com/s/1JE4jCFfC9yBWxvr43GefNA?pwd=xcyx",
    "quark": "https://pan.quark.cn/s/21dffe26cc4e",
    "isNew": false
  },
  {
    "name": "飞越13号房 v1.0.28.3804",
    "baidu": "https://pan.baidu.com/s/19vfozlMf6pJLse5MpTN5qQ?pwd=xcyx",
    "quark": "https://pan.quark.cn/s/1c5112d2f5be",
    "isNew": false
  },
  {
    "name": "魅魔的游戏 v20251205",
    "baidu": "https://pan.baidu.com/s/1K-4qff0kSbcQ89IXqHZ0tw?pwd=xcyx",
    "quark": "https://pan.quark.cn/s/a9d27985090b",
    "isNew": false
  },
  {
    "name": "Beta Kafe Write Your Love Story 官方中文",
    "baidu": "https://pan.baidu.com/s/1LRxDtMvINA9PbL0b_y4Bsw?pwd=xcyx",
    "quark": "https://pan.quark.cn/s/a129e9e00ea1",
    "isNew": false
  },
  {
    "name": "Dreams and Desires 支持VR 英文原版",
    "baidu": "https://pan.baidu.com/s/1gEIak8QbC66hZrO-QcdrRg?pwd=xcyx",
    "quark": "https://pan.quark.cn/s/748510789db9",
    "isNew": false
  },
  {
    "name": "Miss World世界小姐养成日记 本体+开启章节存档",
    "baidu": "https://pan.baidu.com/s/1RJwjkgMev3UUCvd4FRe_pA?pwd=xcyx",
    "quark": "https://pan.quark.cn/s/9b0e60b4ac73",
    "isNew": false
  },
  {
    "name": "下一个就是你",
    "baidu": "https://pan.baidu.com/s/1B0XSBy0d6G5o05BqHrKnsw?pwd=xcyx",
    "quark": "https://pan.quark.cn/s/20eac847d2ca",
    "isNew": false
  },
  {
    "name": "不恋爱就完蛋了",
    "baidu": "https://pan.baidu.com/s/1BafUK-e9YUHw_5jJXweeww?pwd=xcyx",
    "quark": "https://pan.quark.cn/s/7884828fc54d",
    "isNew": false
  },
  {
    "name": "与美女合租的99种死法",
    "baidu": "https://pan.baidu.com/s/1BeuQnNobiuN_yfhRGeLHag?pwd=xcyx",
    "quark": "https://pan.quark.cn/s/535a13ea3f3d",
    "isNew": false
  },
  {
    "name": "主角 demo",
    "baidu": "https://pan.baidu.com/s/19C676IVkLkw0BwDe0z0L3w?pwd=xcyx",
    "quark": "https://pan.quark.cn/s/b06cff868dec",
    "isNew": false
  },
  {
    "name": "九死无生",
    "baidu": "https://pan.baidu.com/s/1Ry_Zr3f4Jtutx0_no6ZO-g?pwd=xcyx",
    "quark": "https://pan.quark.cn/s/afae436acfe7",
    "isNew": false
  },
  {
    "name": "做怡红院的主人",
    "baidu": "https://pan.baidu.com/s/1xr1hJ75kImRZMmOFdyyeOA?pwd=xcyx",
    "quark": "https://pan.quark.cn/s/849afb39d2b9",
    "isNew": false
  },
  {
    "name": "出马-民俗恐怖",
    "baidu": "https://pan.baidu.com/s/1j8tzXJlKEfpu9R79S53fqw?pwd=xcyx",
    "quark": "https://pan.quark.cn/s/272c80514a21",
    "isNew": false
  },
  {
    "name": "反转21克 全DLC 暗夜幽影+迷雾中的真相+命运红线 免登录",
    "baidu": "https://pan.baidu.com/s/14NsNBXfSskfBjr5ieLLBUg?pwd=xcyx",
    "quark": "https://pan.quark.cn/s/51c0d9d237b8",
    "isNew": false
  },
  {
    "name": "台北仲夏夜之梦",
    "baidu": "https://pan.baidu.com/s/1uDOc969TR9-br_1hrcruzw?pwd=xcyx",
    "quark": "https://pan.quark.cn/s/2257330cf1d7",
    "isNew": false
  },
  {
    "name": "名利场 我被好莱坞美女潜规则了",
    "baidu": "https://pan.baidu.com/s/1V6n3fSNzJEtqjJ4jHN0Ehw?pwd=xcyx",
    "quark": "https://pan.quark.cn/s/65c68999ed09",
    "isNew": false
  },
  {
    "name": "命中注定就是你 전설의 반팅",
    "baidu": "https://pan.baidu.com/s/1xukmBmJWHetFsZ1GOkMe3A?pwd=xcyx",
    "quark": "https://pan.quark.cn/s/ae280cf01913",
    "isNew": false
  },
  {
    "name": "命运游戏3：王者棋局 官方中文",
    "baidu": "https://pan.baidu.com/s/1XRPoxFbZolhCOb0KRpY_IQ?pwd=xcyx",
    "quark": "https://pan.quark.cn/s/865b7ef6bdf1",
    "isNew": false
  },
  {
    "name": "哀鸿：城破十日记 全DLC 官方中文",
    "baidu": "https://pan.baidu.com/s/1-8qTae9GsIIOrEXlCiuexA?pwd=xcyx",
    "quark": "https://pan.quark.cn/s/aa4222dff1db",
    "isNew": false
  },
  {
    "name": "哎呦 怎么这么多美女呀！8K 官方中文",
    "baidu": "https://pan.baidu.com/s/18brDw-ZolYFnTPJ7tyuhxQ?pwd=xcyx",
    "quark": "https://pan.quark.cn/s/07d01b428555",
    "isNew": false
  },
  {
    "name": "哦莫！美女们的闪婚修罗场 demo",
    "baidu": "https://pan.baidu.com/s/1Nu_0OeFquR1Cu--ktv9W-w?pwd=xcyx",
    "quark": "https://pan.quark.cn/s/4c968467e4b1",
    "isNew": false
  },
  {
    "name": "四重奏 高跟鞋,魔法,瑜伽与搜查",
    "baidu": "https://pan.baidu.com/s/18ZtOZEDNmkaeO6KqRFFF2Q?pwd=xcyx",
    "quark": "https://pan.quark.cn/s/f02432a01172",
    "isNew": false
  },
  {
    "name": "复体 The Complex 官方中文",
    "baidu": "https://pan.baidu.com/s/1RSbOP0CFxlcFND5fk3TFUA?pwd=xcyx",
    "quark": "https://pan.quark.cn/s/afc4754428f3",
    "isNew": false
  },
  {
    "name": "夏日盛宴",
    "baidu": "https://pan.baidu.com/s/1PsuQVozneRGuDm9PvKFo7w?pwd=xcyx",
    "quark": "https://pan.quark.cn/s/219d8975d8e2",
    "isNew": false
  },
  {
    "name": "天呐！我该怎么选？",
    "baidu": "https://pan.baidu.com/s/1nCT8G0WQaqMHK9i2e-aGUA?pwd=xcyx",
    "quark": "https://pan.quark.cn/s/6604c26c4413",
    "isNew": false
  },
  {
    "name": "好久不见",
    "baidu": "https://pan.baidu.com/s/17bFvAWCCS-J38w9hNFE-hA?pwd=xcyx",
    "quark": "https://pan.quark.cn/s/db5efdb637a8",
    "isNew": false
  },
  {
    "name": "始于谎言的夏日恋情 v1.1.0 官方中文 全DLC",
    "baidu": "https://pan.baidu.com/s/17RqS1tgsgXMfeVuyhkhDaw?pwd=xcyx",
    "quark": "https://pan.quark.cn/s/243705a2c3cd",
    "isNew": false
  },
  {
    "name": "审判者",
    "baidu": "https://pan.baidu.com/s/1YQvZfdxxwDRtl-7_g7AFVg?pwd=xcyx",
    "quark": "https://pan.quark.cn/s/37c39e23480d",
    "isNew": false
  },
  {
    "name": "导演，请多多指教",
    "baidu": "https://pan.baidu.com/s/15Xdxsh7Tkh-7HmKpw2qcJw?pwd=xcyx",
    "quark": "https://pan.quark.cn/s/a57b18e78a57",
    "isNew": false
  },
  {
    "name": "就是个混蛋 v0.31 精翻汉化 城市英雄 Son of a bitch",
    "baidu": "https://pan.baidu.com/s/1oStZaVOGU66a4ChcMJSm5w?pwd=xcyx",
    "quark": "https://pan.quark.cn/s/9b2410e0c45e",
    "isNew": false
  },
  {
    "name": "山河旅探 全DLC 官方中文",
    "baidu": "https://pan.baidu.com/s/11fUC0nP6EYymxHmd0sMtkw?pwd=xcyx",
    "quark": "https://pan.quark.cn/s/99c58244ea25",
    "isNew": false
  },
  {
    "name": "幽林深处 Heart of the Forest",
    "baidu": "https://pan.baidu.com/s/1O0KH51ak2N9eV2ysf63hog?pwd=xcyx",
    "quark": "https://pan.quark.cn/s/371a2c6e86e3",
    "isNew": false
  },
  {
    "name": "底特律：变人 底特律：化身为人 Detroit  Become Human 官方中文",
    "baidu": "https://pan.baidu.com/s/1z36EGyn7gJDaV_xGbTE9UQ?pwd=xcyx",
    "quark": "https://pan.quark.cn/s/7011d2826d6d",
    "isNew": false
  },
  {
    "name": "开局5个亿+存档",
    "baidu": "https://pan.baidu.com/s/1i4rHpqr-o5C8wUZHAKqWDw?pwd=xcyx",
    "quark": "https://pan.quark.cn/s/30047802c9ce",
    "isNew": false
  },
  {
    "name": "心动恋旅：樱花篇",
    "baidu": "https://pan.baidu.com/s/1KXNyGkNsZPAojJa_lcTA0A?pwd=xcyx",
    "quark": "https://pan.quark.cn/s/1a5e9c3b293e",
    "isNew": false
  },
  {
    "name": "心动现场：恋爱实境秀 Heartbeat House  Hong Kong",
    "baidu": "https://pan.baidu.com/s/1W8SX0cVSUeaMKfkts3-CyQ?pwd=xcyx",
    "quark": "https://pan.quark.cn/s/40a1c5693381",
    "isNew": false
  },
  {
    "name": "怦然心动的他们+剧情玩法扩展包",
    "baidu": "https://pan.baidu.com/s/1r0BncX4x9U2aDKaDovxwUw?pwd=xcyx",
    "quark": "https://pan.quark.cn/s/64ffc1c0c38a",
    "isNew": false
  },
  {
    "name": "恋爱吗？我家猫会后空翻 100%全解锁存档 免登录",
    "baidu": "https://pan.baidu.com/s/1VCuJGbHj4wRn7hU3CTjvtA?pwd=xcyx",
    "quark": "https://pan.quark.cn/s/6cfd91a92690",
    "isNew": false
  },
  {
    "name": "恋爱总动员",
    "baidu": "https://pan.baidu.com/s/1QVt9s5Phb_IJ50UWk1ym5w?pwd=xcyx",
    "quark": "https://pan.quark.cn/s/428a645c58ea",
    "isNew": false
  },
  {
    "name": "恋爱模拟器 Love Simulation",
    "baidu": "https://pan.baidu.com/s/1MHrxMlxMkAE3q9hAH6WN4A?pwd=xcyx",
    "quark": "https://pan.quark.cn/s/5b83d9a595f0",
    "isNew": false
  },
  {
    "name": "情感反诈模拟器 捞女游戏 安卓版 官方中文",
    "baidu": "https://pan.baidu.com/s/1Y5hfmO_fYz9kkx7bpkI45Q?pwd=xcyx",
    "quark": "https://pan.quark.cn/s/d0b71afb10b0",
    "isNew": false
  },
  {
    "name": "我和未来有个约定",
    "baidu": "https://pan.baidu.com/s/1CGUU5XGiWEc5-RBDuQDy0A?pwd=xcyx",
    "quark": "https://pan.quark.cn/s/611b9fe65111",
    "isNew": false
  },
  {
    "name": "我打不过漂亮的她们 官方中文",
    "baidu": "https://pan.baidu.com/s/1cGkuma-EtCJYpZSBOa9lmQ?pwd=xcyx",
    "quark": "https://pan.quark.cn/s/f3b30b9ee543",
    "isNew": false
  },
  {
    "name": "我的26岁女房客：在云端 My 26-Year-Old Female Tenant",
    "baidu": "https://pan.baidu.com/s/1JBxrl500NGC9c1HKyKmdeQ?pwd=xcyx",
    "quark": "https://pan.quark.cn/s/a4ebfebbca2e",
    "isNew": false
  },
  {
    "name": "我的时光：大学日记",
    "baidu": "https://pan.baidu.com/s/1NbC_a-bG6OGAKiKKkPapWw?pwd=xcyx",
    "quark": "https://pan.quark.cn/s/1e867529ecdb",
    "isNew": false
  },
  {
    "name": "扫毒风暴：宛北往事",
    "baidu": "https://pan.baidu.com/s/1pSb4eq5_iERp24fDm8EF6w?pwd=xcyx",
    "quark": "https://pan.quark.cn/s/862d098937a0",
    "isNew": false
  },
  {
    "name": "拜托！明天和我恋爱吧",
    "baidu": "https://pan.baidu.com/s/121pkaOto7d6KiR_Yz7OrNQ?pwd=xcyx",
    "quark": "https://pan.quark.cn/s/f4c351a64d33",
    "isNew": false
  },
  {
    "name": "拜托！请你先告白",
    "baidu": "https://pan.baidu.com/s/1ix1KNuRW5UKTp0w5oe9Log?pwd=xcyx",
    "quark": "https://pan.quark.cn/s/4eccb68ed735",
    "isNew": false
  },
  {
    "name": "拟像3 官方中文 SIMULACRA 3",
    "baidu": "https://pan.baidu.com/s/1X2pLWI8jREt6bajmCcdzRg?pwd=xcyx",
    "quark": "https://pan.quark.cn/s/fa31d1233221",
    "isNew": false
  },
  {
    "name": "救命啊 这个是真的喜欢！",
    "baidu": "https://pan.baidu.com/s/1pk__b1yjrdGnAlN-mwEJXw?pwd=xcyx",
    "quark": "https://pan.quark.cn/s/276a4839323f",
    "isNew": false
  },
  {
    "name": "数字心跳：未来制造局",
    "baidu": "https://pan.baidu.com/s/1kHDOptprLJz-_E23P9BgoQ?pwd=xcyx",
    "quark": "https://pan.quark.cn/s/82e86e5e40b4",
    "isNew": false
  },
  {
    "name": "无基之谈",
    "baidu": "https://pan.baidu.com/s/1RtEWdUnG4xRH5pgv_GxhPw?pwd=xcyx",
    "quark": "https://pan.quark.cn/s/6f4d9e082554",
    "isNew": false
  },
  {
    "name": "无声无色",
    "baidu": "https://pan.baidu.com/s/16XcaIuKnoptS0XB8mOb-bQ?pwd=xcyx",
    "quark": "https://pan.quark.cn/s/d7cda39e39dc",
    "isNew": false
  },
  {
    "name": "时空重构",
    "baidu": "https://pan.baidu.com/s/1z3lvslgrgt61jid5Pjv8Aw?pwd=xcyx",
    "quark": "https://pan.quark.cn/s/5d42f0a72f79",
    "isNew": false
  },
  {
    "name": "星梦轨迹-中国式经纪人",
    "baidu": "https://pan.baidu.com/s/15IwMELBvK1KhDogQcUIpUw?pwd=xcyx",
    "quark": "https://pan.quark.cn/s/a156f3bbda18",
    "isNew": false
  },
  {
    "name": "春逝百年抄 The Centennial Case  A Shijima Story",
    "baidu": "https://pan.baidu.com/s/1f_jLtkhe9R5PGEN29vJEEg?pwd=xcyx",
    "quark": "https://pan.quark.cn/s/46aa9c4c0058",
    "isNew": false
  },
  {
    "name": "晨昏线",
    "baidu": "https://pan.baidu.com/s/1rrJKHeChDTdmreMG_udOqA?pwd=xcyx",
    "quark": "https://pan.quark.cn/s/18537d50916a",
    "isNew": false
  },
  {
    "name": "末日降临！被美女们关进避难所!",
    "baidu": "https://pan.baidu.com/s/1uIlzRU-iUBK7aJulV5sOnA?pwd=xcyx",
    "quark": "https://pan.quark.cn/s/b672d62b2fe9",
    "isNew": false
  },
  {
    "name": "杠精的108种死法",
    "baidu": "https://pan.baidu.com/s/1ZEEwwpRO50_w0BWQJWJIZg?pwd=xcyx",
    "quark": "https://pan.quark.cn/s/4b1c9b0bb57c",
    "isNew": false
  },
  {
    "name": "极品采花郎 v1.44+存档 官方中文",
    "baidu": "https://pan.baidu.com/s/1EHYIsVxj2ZSYEDVoLM7NIg?pwd=xcyx",
    "quark": "https://pan.quark.cn/s/f539e84e3c3f",
    "isNew": false
  },
  {
    "name": "极速约会夏日版",
    "baidu": "https://pan.baidu.com/s/1BmjaO4CbTkz6NKHxYnQzgA?pwd=xcyx",
    "quark": "https://pan.quark.cn/s/f4c96f378a75",
    "isNew": false
  },
  {
    "name": "极速营救 更新新版本 v2025820",
    "baidu": "https://pan.baidu.com/s/1x_eEm5wYRTT4yCpV8UWEOA?pwd=xcyx",
    "quark": "https://pan.quark.cn/s/c4c64eaf6ad7",
    "isNew": false
  },
  {
    "name": "林葬屋前传：冥声",
    "baidu": "https://pan.baidu.com/s/1ByA8A3JcmS5sV39u9nbvtg?pwd=xcyx",
    "quark": "https://pan.quark.cn/s/2ddb6d61dc7e",
    "isNew": false
  },
  {
    "name": "树上的经纬线 缘起",
    "baidu": "https://pan.baidu.com/s/1mFoijUm_bu2547PH-vyokw?pwd=xcyx",
    "quark": "https://pan.quark.cn/s/1b7a5da22bbf",
    "isNew": false
  },
  {
    "name": "比基尼和小拳拳 官方中文",
    "baidu": "https://pan.baidu.com/s/1bJiL6Hp4IyqlhLYSt_5bxw?pwd=xcyx",
    "quark": "https://pan.quark.cn/s/323bffd4373d",
    "isNew": false
  },
  {
    "name": "江山北望 最终修复版本 Final Version 免登录",
    "baidu": "https://pan.baidu.com/s/1324Fuem-Gm659fhX3XUKXA?pwd=xcyx",
    "quark": "https://pan.quark.cn/s/c4cf126b2cca",
    "isNew": false
  },
  {
    "name": "法医探案团之碎嘴小诗",
    "baidu": "https://pan.baidu.com/s/1I0f3iY3FU9jXTRMH45BVWA?pwd=xcyx",
    "quark": "https://pan.quark.cn/s/233a6875d33c",
    "isNew": false
  },
  {
    "name": "泳衣封神榜 银魔姜子牙",
    "baidu": "https://pan.baidu.com/s/1iv7-nLZvn1fQkuXXMMYgmQ?pwd=xcyx",
    "quark": "https://pan.quark.cn/s/4f9af00792f6",
    "isNew": false
  },
  {
    "name": "深海：即刻抉择",
    "baidu": "https://pan.baidu.com/s/1B7cewso0uGmZ0r6dDWoIWg?pwd=xcyx",
    "quark": "https://pan.quark.cn/s/cd2fdecfdc8b",
    "isNew": false
  },
  {
    "name": "炸鸡游戏",
    "baidu": "https://pan.baidu.com/s/1xNmvHKvIBHPGitw1ZMFWAw?pwd=xcyx",
    "quark": "https://pan.quark.cn/s/1dd2c51610d6",
    "isNew": false
  },
  {
    "name": "炽澜号 V20251018本体+沉浸电影画面风格包",
    "baidu": "https://pan.baidu.com/s/1JNWc3Zc5u7hWz8I83vAJ5w?pwd=xcyx",
    "quark": "https://pan.quark.cn/s/f0fe33d51711",
    "isNew": false
  },
  {
    "name": "爱情在起航",
    "baidu": "https://pan.baidu.com/s/1urspz3O9PUpCCA5E5sRQKw?pwd=xcyx",
    "quark": "https://pan.quark.cn/s/6625f2461820",
    "isNew": false
  },
  {
    "name": "爱情大师 Master of Love",
    "baidu": "https://pan.baidu.com/s/1LtwM7W1rR5EE5zdX2Df7VA?pwd=xcyx",
    "quark": "https://pan.quark.cn/s/f45889fd0fd4",
    "isNew": false
  },
  {
    "name": "狂想夏日盛宴",
    "baidu": "https://pan.baidu.com/s/1HXee1tErt8UQ3cd7Rvux2w?pwd=xcyx",
    "quark": "https://pan.quark.cn/s/5ee871288383",
    "isNew": false
  },
  {
    "name": "玉足俱乐部",
    "baidu": "https://pan.baidu.com/s/1YpQwd_lgjAWUwDP161WdbA?pwd=xcyx",
    "quark": "https://pan.quark.cn/s/d27e65279107",
    "isNew": false
  },
  {
    "name": "玉足俱乐部2 EPIC官中",
    "baidu": "https://pan.baidu.com/s/1HQscXlvRkDGlTI3BhsG70g?pwd=xcyx",
    "quark": "https://pan.quark.cn/s/f757e8ae3dd5",
    "isNew": false
  },
  {
    "name": "甜心AI追捕计划+4K画质补丁包",
    "baidu": "https://pan.baidu.com/s/1owptaVo7qVjEnLU-tdCSww?pwd=xcyx",
    "quark": "https://pan.quark.cn/s/aa974d136860",
    "isNew": false
  },
  {
    "name": "监寓",
    "baidu": "https://pan.baidu.com/s/1IjylejfCerp8yE1JaMYY5A?pwd=xcyx",
    "quark": "https://pan.quark.cn/s/172abccd6920",
    "isNew": false
  },
  {
    "name": "神都不良探+全章节DLC Underdog Detective",
    "baidu": "https://pan.baidu.com/s/15O6dTLwSzsCSZcSuGoDpnw?pwd=xcyx",
    "quark": "https://pan.quark.cn/s/858e99126fbb",
    "isNew": false
  },
  {
    "name": "禁地直播 官方中文",
    "baidu": "https://pan.baidu.com/s/1VcNshpFzY7YEwDmX1KClVA?pwd=xcyx",
    "quark": "https://pan.quark.cn/s/965156f56ee3",
    "isNew": false
  },
  {
    "name": "私人定制：我的专属韩国女团",
    "baidu": "https://pan.baidu.com/s/1T9mx28M44CdfFhIow0TK-Q?pwd=xcyx",
    "quark": "https://pan.quark.cn/s/e84fc4c61bfb",
    "isNew": false
  },
  {
    "name": "美女 游泳健身了解一下 官方中文",
    "baidu": "https://pan.baidu.com/s/1R9TIwPATY7Ukm7I25ndSzw?pwd=xcyx",
    "quark": "https://pan.quark.cn/s/8d1ad03ebd15",
    "isNew": false
  },
  {
    "name": "老师学生都爱上我 Theteacherlovewithme",
    "baidu": "https://pan.baidu.com/s/1PI7Z3H0ULzmYPdUEltB2fA?pwd=xcyx",
    "quark": "https://pan.quark.cn/s/139ace3b61c3",
    "isNew": false
  },
  {
    "name": "老师学生都爱上我2 Theteacherfellinloveo2hKz",
    "baidu": "https://pan.baidu.com/s/1Powj1rPEeRMz8Gn_ERon6Q?pwd=xcyx",
    "quark": "https://pan.quark.cn/s/f575d5454ab6",
    "isNew": false
  },
  {
    "name": "背后Back",
    "baidu": "https://pan.baidu.com/s/1dus_GXiDvzh0zvUbZmxP5Q?pwd=xcyx",
    "quark": "https://pan.quark.cn/s/f26e5c662213",
    "isNew": false
  },
  {
    "name": "舔狗三年 官方中文",
    "baidu": "https://pan.baidu.com/s/1AcP90qGjhKbt70oobnHe6g?pwd=xcyx",
    "quark": "https://pan.quark.cn/s/86ba187d04b6",
    "isNew": false
  },
  {
    "name": "花奴令",
    "baidu": "https://pan.baidu.com/s/1ZtpfmKk93vAUcFRGKWuLPA?pwd=xcyx",
    "quark": "https://pan.quark.cn/s/d2c210d9d143",
    "isNew": false
  },
  {
    "name": "蜀汉再临：源起",
    "baidu": "https://pan.baidu.com/s/1g7cD5rwufqLKSP_Ky7AQzA?pwd=xcyx",
    "quark": "https://pan.quark.cn/s/d8bb1effb5da",
    "isNew": false
  },
  {
    "name": "规则怪谈：梦核密室逃脱",
    "baidu": "https://pan.baidu.com/s/1Tn8e-xEg4XoqNP0Uh8NqiA?pwd=xcyx",
    "quark": "https://pan.quark.cn/s/b1ce28abc569",
    "isNew": false
  },
  {
    "name": "说谎 Telling Lies",
    "baidu": "https://pan.baidu.com/s/1dYLF1W6LuXUJakRQspZT2w?pwd=xcyx",
    "quark": "https://pan.quark.cn/s/1e845d31a4ef",
    "isNew": false
  },
  {
    "name": "请做coser的主人1",
    "baidu": "https://pan.baidu.com/s/15bTDhzjuCz8rHUVSo6ZT_g?pwd=xcyx",
    "quark": "https://pan.quark.cn/s/5c1e7a0e2ca5",
    "isNew": false
  },
  {
    "name": "请做coser的主人10",
    "baidu": "https://pan.baidu.com/s/1gUupeF2ltBDnO5QDXZHMEA?pwd=xcyx",
    "quark": "https://pan.quark.cn/s/40421f31737a",
    "isNew": false
  },
  {
    "name": "请做coser的主人11",
    "baidu": "https://pan.baidu.com/s/1dayhgOZIQM0ei0iVm0qzyA?pwd=xcyx",
    "quark": "https://pan.quark.cn/s/b88f7eb5e6d6",
    "isNew": false
  },
  {
    "name": "请做coser的主人12",
    "baidu": "https://pan.baidu.com/s/168EbRZEG8EbuaQatRrjW-Q?pwd=xcyx",
    "quark": "https://pan.quark.cn/s/f46d94662687",
    "isNew": false
  },
  {
    "name": "请做coser的主人13",
    "baidu": "https://pan.baidu.com/s/1mmtvERr38buNECfWubxbOw?pwd=xcyx",
    "quark": "https://pan.quark.cn/s/e54d9f59b218",
    "isNew": false
  },
  {
    "name": "请做coser的主人14",
    "baidu": "https://pan.baidu.com/s/1a8BHZgjome4cojT6kgPklQ?pwd=xcyx",
    "quark": "https://pan.quark.cn/s/296072ceb339",
    "isNew": false
  },
  {
    "name": "请做coser的主人2",
    "baidu": "https://pan.baidu.com/s/1kmmWvpO06391CiY-6r3AnQ?pwd=xcyx",
    "quark": "https://pan.quark.cn/s/ebad1280e787",
    "isNew": false
  },
  {
    "name": "请做coser的主人3",
    "baidu": "https://pan.baidu.com/s/1YBIUp0gH75N-iRwzA6vxwg?pwd=xcyx",
    "quark": "https://pan.quark.cn/s/fbce545d75af",
    "isNew": false
  },
  {
    "name": "请做coser的主人4",
    "baidu": "https://pan.baidu.com/s/1MIXfmHSJsDHaQDW1Rsq91A?pwd=xcyx",
    "quark": "https://pan.quark.cn/s/122ae9711c37",
    "isNew": false
  },
  {
    "name": "请做coser的主人6",
    "baidu": "https://pan.baidu.com/s/1Xbq-0py-ejdagC9OC091Iw?pwd=xcyx",
    "quark": "https://pan.quark.cn/s/d68fa8b26b9b",
    "isNew": false
  },
  {
    "name": "请做coser的主人7",
    "baidu": "https://pan.baidu.com/s/1EUHi9oBp8XexCkTiViBuhQ?pwd=xcyx",
    "quark": "https://pan.quark.cn/s/05f12a69bdb2",
    "isNew": false
  },
  {
    "name": "请做coser的主人8",
    "baidu": "https://pan.baidu.com/s/1OYBfp7wG1cpurkJMRKW4qQ?pwd=xcyx",
    "quark": "https://pan.quark.cn/s/1db3f9577fee",
    "isNew": false
  },
  {
    "name": "请做coser的主人9",
    "baidu": "https://pan.baidu.com/s/1bd41FwnZwwvhYF8RLUtpfw?pwd=xcyx",
    "quark": "https://pan.quark.cn/s/00342837f5f1",
    "isNew": false
  },
  {
    "name": "请叫我英雄",
    "baidu": "https://pan.baidu.com/s/1Y1Ou_VY0i-7nJ7-Q5zeFDg?pwd=xcyx",
    "quark": "https://pan.quark.cn/s/ab954f7dbd32",
    "isNew": false
  },
  {
    "name": "返杀 Back Fire",
    "baidu": "https://pan.baidu.com/s/1fPh0oyvvKhFM_oiNNPrFBA?pwd=xcyx",
    "quark": "https://pan.quark.cn/s/9e77e997caf4",
    "isNew": false
  },
  {
    "name": "进击吧，异次元美少女!",
    "baidu": "https://pan.baidu.com/s/1nSr_ECIalvoPfv7QRqeuOg?pwd=xcyx",
    "quark": "https://pan.quark.cn/s/bf576d45c05c",
    "isNew": false
  },
  {
    "name": "金瓶梅1 官方中文",
    "baidu": "https://pan.baidu.com/s/1WLQWW-Bzhtd9Jf9bzDn9OA?pwd=xcyx",
    "quark": "https://pan.quark.cn/s/a2d8a8ccd7b0",
    "isNew": false
  },
  {
    "name": "金瓶梅3 The Plum in the Golden Vase 3",
    "baidu": "https://pan.baidu.com/s/1ob5AV0ozlBPYx6hkFHeQSg?pwd=xcyx",
    "quark": "https://pan.quark.cn/s/4470b60c2a63",
    "isNew": false
  },
  {
    "name": "银魔唐三藏",
    "baidu": "https://pan.baidu.com/s/1xsi7rVyzgAesbO7GSO9v3Q?pwd=xcyx",
    "quark": "https://pan.quark.cn/s/6db5e8a765b0",
    "isNew": false
  }
]